<?xml version="1.0"?>
<icons default="action/3d_rotation">
 <option id="action/3d_rotation">action/3d_rotation</option>
 <option id="action/accessibility">action/accessibility</option>
 <option id="action/accessibility_new">action/accessibility_new</option>
 <option id="action/accessible">action/accessible</option>
 <option id="action/accessible_forward">action/accessible_forward</option>
 <option id="action/account_balance">action/account_balance</option>
 <option id="action/account_balance_wallet">action/account_balance_wallet</option>
 <option id="action/account_box">action/account_box</option>
 <option id="action/account_circle">action/account_circle</option>
 <option id="action/add_shopping_cart">action/add_shopping_cart</option>
 <option id="action/alarm">action/alarm</option>
 <option id="action/alarm_add">action/alarm_add</option>
 <option id="action/alarm_off">action/alarm_off</option>
 <option id="action/alarm_on">action/alarm_on</option>
 <option id="action/all_inbox">action/all_inbox</option>
 <option id="action/all_out">action/all_out</option>
 <option id="action/android">action/android</option>
 <option id="action/announcement">action/announcement</option>
 <option id="action/arrow_right_alt">action/arrow_right_alt</option>
 <option id="action/aspect_ratio">action/aspect_ratio</option>
 <option id="action/assessment">action/assessment</option>
 <option id="action/assignment">action/assignment</option>
 <option id="action/assignment_ind">action/assignment_ind</option>
 <option id="action/assignment_late">action/assignment_late</option>
 <option id="action/assignment_return">action/assignment_return</option>
 <option id="action/assignment_returned">action/assignment_returned</option>
 <option id="action/assignment_turned_in">action/assignment_turned_in</option>
 <option id="action/autorenew">action/autorenew</option>
 <option id="action/backup">action/backup</option>
 <option id="action/book">action/book</option>
 <option id="action/bookmark">action/bookmark</option>
 <option id="action/bookmark_border">action/bookmark_border</option>
 <option id="action/bookmarks">action/bookmarks</option>
 <option id="action/bug_report">action/bug_report</option>
 <option id="action/build">action/build</option>
 <option id="action/cached">action/cached</option>
 <option id="action/calendar_today">action/calendar_today</option>
 <option id="action/calendar_view_day">action/calendar_view_day</option>
 <option id="action/camera_enhance">action/camera_enhance</option>
 <option id="action/cancel_schedule_send">action/cancel_schedule_send</option>
 <option id="action/card_giftcard">action/card_giftcard</option>
 <option id="action/card_membership">action/card_membership</option>
 <option id="action/card_travel">action/card_travel</option>
 <option id="action/change_history">action/change_history</option>
 <option id="action/check_circle">action/check_circle</option>
 <option id="action/check_circle_outline">action/check_circle_outline</option>
 <option id="action/chrome_reader_mode">action/chrome_reader_mode</option>
 <option id="action/class">action/class</option>
 <option id="action/code">action/code</option>
 <option id="action/commute">action/commute</option>
 <option id="action/compare_arrows">action/compare_arrows</option>
 <option id="action/contact_support">action/contact_support</option>
 <option id="action/contactless">action/contactless</option>
 <option id="action/copyright">action/copyright</option>
 <option id="action/credit_card">action/credit_card</option>
 <option id="action/dashboard">action/dashboard</option>
 <option id="action/date_range">action/date_range</option>
 <option id="action/delete">action/delete</option>
 <option id="action/delete_forever">action/delete_forever</option>
 <option id="action/delete_outline">action/delete_outline</option>
 <option id="action/description">action/description</option>
 <option id="action/dns">action/dns</option>
 <option id="action/done">action/done</option>
 <option id="action/done_all">action/done_all</option>
 <option id="action/done_outline">action/done_outline</option>
 <option id="action/donut_large">action/donut_large</option>
 <option id="action/donut_small">action/donut_small</option>
 <option id="action/drag_indicator">action/drag_indicator</option>
 <option id="action/eco">action/eco</option>
 <option id="action/eject">action/eject</option>
 <option id="action/euro_symbol">action/euro_symbol</option>
 <option id="action/event">action/event</option>
 <option id="action/event_seat">action/event_seat</option>
 <option id="action/exit_to_app">action/exit_to_app</option>
 <option id="action/explore">action/explore</option>
 <option id="action/explore_off">action/explore_off</option>
 <option id="action/extension">action/extension</option>
 <option id="action/face">action/face</option>
 <option id="action/favorite">action/favorite</option>
 <option id="action/favorite_border">action/favorite_border</option>
 <option id="action/feedback">action/feedback</option>
 <option id="action/find_in_page">action/find_in_page</option>
 <option id="action/find_replace">action/find_replace</option>
 <option id="action/fingerprint">action/fingerprint</option>
 <option id="action/flight_land">action/flight_land</option>
 <option id="action/flight_takeoff">action/flight_takeoff</option>
 <option id="action/flip_to_back">action/flip_to_back</option>
 <option id="action/flip_to_front">action/flip_to_front</option>
 <option id="action/g_translate">action/g_translate</option>
 <option id="action/gavel">action/gavel</option>
 <option id="action/get_app">action/get_app</option>
 <option id="action/gif">action/gif</option>
 <option id="action/grade">action/grade</option>
 <option id="action/group_work">action/group_work</option>
 <option id="action/help">action/help</option>
 <option id="action/help_outline">action/help_outline</option>
 <option id="action/highlight_off">action/highlight_off</option>
 <option id="action/history">action/history</option>
 <option id="action/home">action/home</option>
 <option id="action/horizontal_split">action/horizontal_split</option>
 <option id="action/hourglass_empty">action/hourglass_empty</option>
 <option id="action/hourglass_full">action/hourglass_full</option>
 <option id="action/http">action/http</option>
 <option id="action/https">action/https</option>
 <option id="action/important_devices">action/important_devices</option>
 <option id="action/info">action/info</option>
 <option id="action/input">action/input</option>
 <option id="action/invert_colors">action/invert_colors</option>
 <option id="action/label">action/label</option>
 <option id="action/label_important">action/label_important</option>
 <option id="action/label_off">action/label_off</option>
 <option id="action/language">action/language</option>
 <option id="action/launch">action/launch</option>
 <option id="action/line_style">action/line_style</option>
 <option id="action/line_weight">action/line_weight</option>
 <option id="action/list">action/list</option>
 <option id="action/lock">action/lock</option>
 <option id="action/lock_open">action/lock_open</option>
 <option id="action/loyalty">action/loyalty</option>
 <option id="action/markunread_mailbox">action/markunread_mailbox</option>
 <option id="action/maximize">action/maximize</option>
 <option id="action/minimize">action/minimize</option>
 <option id="action/motorcycle">action/motorcycle</option>
 <option id="action/note_add">action/note_add</option>
 <option id="action/offline_bolt">action/offline_bolt</option>
 <option id="action/offline_pin">action/offline_pin</option>
 <option id="action/opacity">action/opacity</option>
 <option id="action/open_in_browser">action/open_in_browser</option>
 <option id="action/open_in_new">action/open_in_new</option>
 <option id="action/open_with">action/open_with</option>
 <option id="action/pageview">action/pageview</option>
 <option id="action/pan_tool">action/pan_tool</option>
 <option id="action/payment">action/payment</option>
 <option id="action/perm_camera_mic">action/perm_camera_mic</option>
 <option id="action/perm_contact_calendar">action/perm_contact_calendar</option>
 <option id="action/perm_data_setting">action/perm_data_setting</option>
 <option id="action/perm_device_information">action/perm_device_information</option>
 <option id="action/perm_identity">action/perm_identity</option>
 <option id="action/perm_media">action/perm_media</option>
 <option id="action/perm_phone_msg">action/perm_phone_msg</option>
 <option id="action/perm_scan_wifi">action/perm_scan_wifi</option>
 <option id="action/pets">action/pets</option>
 <option id="action/picture_in_picture">action/picture_in_picture</option>
 <option id="action/picture_in_picture_alt">action/picture_in_picture_alt</option>
 <option id="action/play_for_work">action/play_for_work</option>
 <option id="action/polymer">action/polymer</option>
 <option id="action/power_settings_new">action/power_settings_new</option>
 <option id="action/pregnant_woman">action/pregnant_woman</option>
 <option id="action/print">action/print</option>
 <option id="action/query_builder">action/query_builder</option>
 <option id="action/question_answer">action/question_answer</option>
 <option id="action/receipt">action/receipt</option>
 <option id="action/record_voice_over">action/record_voice_over</option>
 <option id="action/redeem">action/redeem</option>
 <option id="action/remove_shopping_cart">action/remove_shopping_cart</option>
 <option id="action/reorder">action/reorder</option>
 <option id="action/report_problem">action/report_problem</option>
 <option id="action/restore">action/restore</option>
 <option id="action/restore_from_trash">action/restore_from_trash</option>
 <option id="action/restore_page">action/restore_page</option>
 <option id="action/room">action/room</option>
 <option id="action/rounded_corner">action/rounded_corner</option>
 <option id="action/rowing">action/rowing</option>
 <option id="action/schedule">action/schedule</option>
 <option id="action/search">action/search</option>
 <option id="action/settings_applications">action/settings_applications</option>
 <option id="action/settings_backup_restore">action/settings_backup_restore</option>
 <option id="action/settings_bluetooth">action/settings_bluetooth</option>
 <option id="action/settings_brightness">action/settings_brightness</option>
 <option id="action/settings_cell">action/settings_cell</option>
 <option id="action/settings_ethernet">action/settings_ethernet</option>
 <option id="action/settings_input_antenna">action/settings_input_antenna</option>
 <option id="action/settings_input_component">action/settings_input_component</option>
 <option id="action/settings_input_composite">action/settings_input_composite</option>
 <option id="action/settings_input_hdmi">action/settings_input_hdmi</option>
 <option id="action/settings_input_svideo">action/settings_input_svideo</option>
 <option id="action/settings_overscan">action/settings_overscan</option>
 <option id="action/settings_phone">action/settings_phone</option>
 <option id="action/settings_power">action/settings_power</option>
 <option id="action/settings_remote">action/settings_remote</option>
 <option id="action/settings_voice">action/settings_voice</option>
 <option id="action/shop">action/shop</option>
 <option id="action/shop_two">action/shop_two</option>
 <option id="action/shopping_basket">action/shopping_basket</option>
 <option id="action/shopping_cart">action/shopping_cart</option>
 <option id="action/speaker_notes">action/speaker_notes</option>
 <option id="action/speaker_notes_off">action/speaker_notes_off</option>
 <option id="action/spellcheck">action/spellcheck</option>
 <option id="action/stars">action/stars</option>
 <option id="action/store">action/store</option>
 <option id="action/subject">action/subject</option>
 <option id="action/supervised_user_circle">action/supervised_user_circle</option>
 <option id="action/supervisor_account">action/supervisor_account</option>
 <option id="action/swap_horiz">action/swap_horiz</option>
 <option id="action/swap_horizontal_circle">action/swap_horizontal_circle</option>
 <option id="action/swap_vert">action/swap_vert</option>
 <option id="action/swap_vertical_circle">action/swap_vertical_circle</option>
 <option id="action/sync_alt">action/sync_alt</option>
 <option id="action/system_update_alt">action/system_update_alt</option>
 <option id="action/tab">action/tab</option>
 <option id="action/tab_unselected">action/tab_unselected</option>
 <option id="action/text_rotate_up">action/text_rotate_up</option>
 <option id="action/text_rotate_vertical">action/text_rotate_vertical</option>
 <option id="action/text_rotation_angledown">action/text_rotation_angledown</option>
 <option id="action/text_rotation_angleup">action/text_rotation_angleup</option>
 <option id="action/text_rotation_down">action/text_rotation_down</option>
 <option id="action/text_rotation_none">action/text_rotation_none</option>
 <option id="action/theaters">action/theaters</option>
 <option id="action/thumb_down">action/thumb_down</option>
 <option id="action/thumb_up">action/thumb_up</option>
 <option id="action/thumbs_up_down">action/thumbs_up_down</option>
 <option id="action/timeline">action/timeline</option>
 <option id="action/toc">action/toc</option>
 <option id="action/today">action/today</option>
 <option id="action/toll">action/toll</option>
 <option id="action/touch_app">action/touch_app</option>
 <option id="action/track_changes">action/track_changes</option>
 <option id="action/translate">action/translate</option>
 <option id="action/trending_down">action/trending_down</option>
 <option id="action/trending_flat">action/trending_flat</option>
 <option id="action/trending_up">action/trending_up</option>
 <option id="action/turned_in">action/turned_in</option>
 <option id="action/turned_in_not">action/turned_in_not</option>
 <option id="action/update">action/update</option>
 <option id="action/verified_user">action/verified_user</option>
 <option id="action/vertical_split">action/vertical_split</option>
 <option id="action/view_agenda">action/view_agenda</option>
 <option id="action/view_array">action/view_array</option>
 <option id="action/view_carousel">action/view_carousel</option>
 <option id="action/view_column">action/view_column</option>
 <option id="action/view_day">action/view_day</option>
 <option id="action/view_headline">action/view_headline</option>
 <option id="action/view_list">action/view_list</option>
 <option id="action/view_module">action/view_module</option>
 <option id="action/view_quilt">action/view_quilt</option>
 <option id="action/view_stream">action/view_stream</option>
 <option id="action/view_week">action/view_week</option>
 <option id="action/visibility">action/visibility</option>
 <option id="action/visibility_off">action/visibility_off</option>
 <option id="action/voice_over_off">action/voice_over_off</option>
 <option id="action/watch_later">action/watch_later</option>
 <option id="action/work">action/work</option>
 <option id="action/work_off">action/work_off</option>
 <option id="action/work_outline">action/work_outline</option>
 <option id="action/youtube_searched_for">action/youtube_searched_for</option>
 <option id="action/zoom_in">action/zoom_in</option>
 <option id="action/zoom_out">action/zoom_out</option>
 <option id="alert/add_alert">alert/add_alert</option>
 <option id="alert/error">alert/error</option>
 <option id="alert/error_outline">alert/error_outline</option>
 <option id="alert/notification_important">alert/notification_important</option>
 <option id="alert/warning">alert/warning</option>
 <option id="av/4k">av/4k</option>
 <option id="av/add_to_queue">av/add_to_queue</option>
 <option id="av/airplay">av/airplay</option>
 <option id="av/album">av/album</option>
 <option id="av/art_track">av/art_track</option>
 <option id="av/av_timer">av/av_timer</option>
 <option id="av/branding_watermark">av/branding_watermark</option>
 <option id="av/call_to_action">av/call_to_action</option>
 <option id="av/closed_caption">av/closed_caption</option>
 <option id="av/control_camera">av/control_camera</option>
 <option id="av/equalizer">av/equalizer</option>
 <option id="av/explicit">av/explicit</option>
 <option id="av/fast_forward">av/fast_forward</option>
 <option id="av/fast_rewind">av/fast_rewind</option>
 <option id="av/featured_play_list">av/featured_play_list</option>
 <option id="av/featured_video">av/featured_video</option>
 <option id="av/fiber_dvr">av/fiber_dvr</option>
 <option id="av/fiber_manual_record">av/fiber_manual_record</option>
 <option id="av/fiber_new">av/fiber_new</option>
 <option id="av/fiber_pin">av/fiber_pin</option>
 <option id="av/fiber_smart_record">av/fiber_smart_record</option>
 <option id="av/forward_10">av/forward_10</option>
 <option id="av/forward_30">av/forward_30</option>
 <option id="av/forward_5">av/forward_5</option>
 <option id="av/games">av/games</option>
 <option id="av/hd">av/hd</option>
 <option id="av/hearing">av/hearing</option>
 <option id="av/high_quality">av/high_quality</option>
 <option id="av/library_add">av/library_add</option>
 <option id="av/library_books">av/library_books</option>
 <option id="av/library_music">av/library_music</option>
 <option id="av/loop">av/loop</option>
 <option id="av/mic">av/mic</option>
 <option id="av/mic_none">av/mic_none</option>
 <option id="av/mic_off">av/mic_off</option>
 <option id="av/missed_video_call">av/missed_video_call</option>
 <option id="av/movie">av/movie</option>
 <option id="av/music_video">av/music_video</option>
 <option id="av/new_releases">av/new_releases</option>
 <option id="av/not_interested">av/not_interested</option>
 <option id="av/note">av/note</option>
 <option id="av/pause">av/pause</option>
 <option id="av/pause_circle_filled">av/pause_circle_filled</option>
 <option id="av/pause_circle_outline">av/pause_circle_outline</option>
 <option id="av/play_arrow">av/play_arrow</option>
 <option id="av/play_circle_filled">av/play_circle_filled</option>
 <option id="av/play_circle_outline">av/play_circle_outline</option>
 <option id="av/playlist_add">av/playlist_add</option>
 <option id="av/playlist_add_check">av/playlist_add_check</option>
 <option id="av/playlist_play">av/playlist_play</option>
 <option id="av/queue">av/queue</option>
 <option id="av/queue_music">av/queue_music</option>
 <option id="av/queue_play_next">av/queue_play_next</option>
 <option id="av/radio">av/radio</option>
 <option id="av/recent_actors">av/recent_actors</option>
 <option id="av/remove_from_queue">av/remove_from_queue</option>
 <option id="av/repeat">av/repeat</option>
 <option id="av/repeat_one">av/repeat_one</option>
 <option id="av/replay">av/replay</option>
 <option id="av/replay_10">av/replay_10</option>
 <option id="av/replay_30">av/replay_30</option>
 <option id="av/replay_5">av/replay_5</option>
 <option id="av/shuffle">av/shuffle</option>
 <option id="av/skip_next">av/skip_next</option>
 <option id="av/skip_previous">av/skip_previous</option>
 <option id="av/slow_motion_video">av/slow_motion_video</option>
 <option id="av/snooze">av/snooze</option>
 <option id="av/sort_by_alpha">av/sort_by_alpha</option>
 <option id="av/speed">av/speed</option>
 <option id="av/stop">av/stop</option>
 <option id="av/subscriptions">av/subscriptions</option>
 <option id="av/subtitles">av/subtitles</option>
 <option id="av/surround_sound">av/surround_sound</option>
 <option id="av/video_call">av/video_call</option>
 <option id="av/video_label">av/video_label</option>
 <option id="av/video_library">av/video_library</option>
 <option id="av/videocam">av/videocam</option>
 <option id="av/videocam_off">av/videocam_off</option>
 <option id="av/volume_down">av/volume_down</option>
 <option id="av/volume_mute">av/volume_mute</option>
 <option id="av/volume_off">av/volume_off</option>
 <option id="av/volume_up">av/volume_up</option>
 <option id="av/web">av/web</option>
 <option id="av/web_asset">av/web_asset</option>
 <option id="communication/business">communication/business</option>
 <option id="communication/call">communication/call</option>
 <option id="communication/call_end">communication/call_end</option>
 <option id="communication/call_made">communication/call_made</option>
 <option id="communication/call_merge">communication/call_merge</option>
 <option id="communication/call_missed">communication/call_missed</option>
 <option id="communication/call_missed_outgoing">communication/call_missed_outgoing</option>
 <option id="communication/call_received">communication/call_received</option>
 <option id="communication/call_split">communication/call_split</option>
 <option id="communication/cancel_presentation">communication/cancel_presentation</option>
 <option id="communication/chat">communication/chat</option>
 <option id="communication/chat_bubble">communication/chat_bubble</option>
 <option id="communication/chat_bubble_outline">communication/chat_bubble_outline</option>
 <option id="communication/clear_all">communication/clear_all</option>
 <option id="communication/comment">communication/comment</option>
 <option id="communication/contact_mail">communication/contact_mail</option>
 <option id="communication/contact_phone">communication/contact_phone</option>
 <option id="communication/contacts">communication/contacts</option>
 <option id="communication/desktop_access_disabled">communication/desktop_access_disabled</option>
 <option id="communication/dialer_sip">communication/dialer_sip</option>
 <option id="communication/dialpad">communication/dialpad</option>
 <option id="communication/domain_disabled">communication/domain_disabled</option>
 <option id="communication/duo">communication/duo</option>
 <option id="communication/email">communication/email</option>
 <option id="communication/forum">communication/forum</option>
 <option id="communication/import_contacts">communication/import_contacts</option>
 <option id="communication/import_export">communication/import_export</option>
 <option id="communication/invert_colors_off">communication/invert_colors_off</option>
 <option id="communication/list_alt">communication/list_alt</option>
 <option id="communication/live_help">communication/live_help</option>
 <option id="communication/mail_outline">communication/mail_outline</option>
 <option id="communication/message">communication/message</option>
 <option id="communication/mobile_screen_share">communication/mobile_screen_share</option>
 <option id="communication/no_sim">communication/no_sim</option>
 <option id="communication/pause_presentation">communication/pause_presentation</option>
 <option id="communication/person_add_disabled">communication/person_add_disabled</option>
 <option id="communication/phone">communication/phone</option>
 <option id="communication/phone_disabled">communication/phone_disabled</option>
 <option id="communication/phone_enabled">communication/phone_enabled</option>
 <option id="communication/phonelink_erase">communication/phonelink_erase</option>
 <option id="communication/phonelink_lock">communication/phonelink_lock</option>
 <option id="communication/phonelink_ring">communication/phonelink_ring</option>
 <option id="communication/phonelink_setup">communication/phonelink_setup</option>
 <option id="communication/portable_wifi_off">communication/portable_wifi_off</option>
 <option id="communication/present_to_all">communication/present_to_all</option>
 <option id="communication/print_disabled">communication/print_disabled</option>
 <option id="communication/ring_volume">communication/ring_volume</option>
 <option id="communication/rss_feed">communication/rss_feed</option>
 <option id="communication/screen_share">communication/screen_share</option>
 <option id="communication/sentiment_satisfied_alt">communication/sentiment_satisfied_alt</option>
 <option id="communication/speaker_phone">communication/speaker_phone</option>
 <option id="communication/stay_current_landscape">communication/stay_current_landscape</option>
 <option id="communication/stay_current_portrait">communication/stay_current_portrait</option>
 <option id="communication/stay_primary_landscape">communication/stay_primary_landscape</option>
 <option id="communication/stay_primary_portrait">communication/stay_primary_portrait</option>
 <option id="communication/stop_screen_share">communication/stop_screen_share</option>
 <option id="communication/swap_calls">communication/swap_calls</option>
 <option id="communication/textsms">communication/textsms</option>
 <option id="communication/unsubscribe">communication/unsubscribe</option>
 <option id="communication/voicemail">communication/voicemail</option>
 <option id="communication/vpn_key">communication/vpn_key</option>
 <option id="content/add">content/add</option>
 <option id="content/add_box">content/add_box</option>
 <option id="content/add_circle">content/add_circle</option>
 <option id="content/add_circle_outline">content/add_circle_outline</option>
 <option id="content/amp_stories">content/amp_stories</option>
 <option id="content/archive">content/archive</option>
 <option id="content/backspace">content/backspace</option>
 <option id="content/ballot">content/ballot</option>
 <option id="content/block">content/block</option>
 <option id="content/clear">content/clear</option>
 <option id="content/create">content/create</option>
 <option id="content/delete_sweep">content/delete_sweep</option>
 <option id="content/drafts">content/drafts</option>
 <option id="content/dynamic_feed">content/dynamic_feed</option>
 <option id="content/file_copy">content/file_copy</option>
 <option id="content/filter_list">content/filter_list</option>
 <option id="content/flag">content/flag</option>
 <option id="content/font_download">content/font_download</option>
 <option id="content/forward">content/forward</option>
 <option id="content/gesture">content/gesture</option>
 <option id="content/how_to_reg">content/how_to_reg</option>
 <option id="content/how_to_vote">content/how_to_vote</option>
 <option id="content/inbox">content/inbox</option>
 <option id="content/link">content/link</option>
 <option id="content/link_off">content/link_off</option>
 <option id="content/low_priority">content/low_priority</option>
 <option id="content/mail">content/mail</option>
 <option id="content/markunread">content/markunread</option>
 <option id="content/move_to_inbox">content/move_to_inbox</option>
 <option id="content/next_week">content/next_week</option>
 <option id="content/outlined_flag">content/outlined_flag</option>
 <option id="content/policy">content/policy</option>
 <option id="content/redo">content/redo</option>
 <option id="content/remove">content/remove</option>
 <option id="content/remove_circle">content/remove_circle</option>
 <option id="content/remove_circle_outline">content/remove_circle_outline</option>
 <option id="content/reply">content/reply</option>
 <option id="content/reply_all">content/reply_all</option>
 <option id="content/report">content/report</option>
 <option id="content/report_off">content/report_off</option>
 <option id="content/save">content/save</option>
 <option id="content/save_alt">content/save_alt</option>
 <option id="content/select_all">content/select_all</option>
 <option id="content/send">content/send</option>
 <option id="content/sort">content/sort</option>
 <option id="content/square_foot">content/square_foot</option>
 <option id="content/text_format">content/text_format</option>
 <option id="content/unarchive">content/unarchive</option>
 <option id="content/undo">content/undo</option>
 <option id="content/waves">content/waves</option>
 <option id="content/where_to_vote">content/where_to_vote</option>
 <option id="device/access_alarm">device/access_alarm</option>
 <option id="device/access_alarms">device/access_alarms</option>
 <option id="device/access_time">device/access_time</option>
 <option id="device/add_alarm">device/add_alarm</option>
 <option id="device/add_to_home_screen">device/add_to_home_screen</option>
 <option id="device/airplanemode_active">device/airplanemode_active</option>
 <option id="device/airplanemode_inactive">device/airplanemode_inactive</option>
 <option id="device/battery_alert">device/battery_alert</option>
 <option id="device/battery_charging_full">device/battery_charging_full</option>
 <option id="device/battery_full">device/battery_full</option>
 <option id="device/battery_std">device/battery_std</option>
 <option id="device/battery_unknown">device/battery_unknown</option>
 <option id="device/bluetooth">device/bluetooth</option>
 <option id="device/bluetooth_connected">device/bluetooth_connected</option>
 <option id="device/bluetooth_disabled">device/bluetooth_disabled</option>
 <option id="device/bluetooth_searching">device/bluetooth_searching</option>
 <option id="device/brightness_auto">device/brightness_auto</option>
 <option id="device/brightness_high">device/brightness_high</option>
 <option id="device/brightness_low">device/brightness_low</option>
 <option id="device/brightness_medium">device/brightness_medium</option>
 <option id="device/data_usage">device/data_usage</option>
 <option id="device/developer_mode">device/developer_mode</option>
 <option id="device/devices">device/devices</option>
 <option id="device/dvr">device/dvr</option>
 <option id="device/gps_fixed">device/gps_fixed</option>
 <option id="device/gps_not_fixed">device/gps_not_fixed</option>
 <option id="device/gps_off">device/gps_off</option>
 <option id="device/graphic_eq">device/graphic_eq</option>
 <option id="device/location_disabled">device/location_disabled</option>
 <option id="device/location_searching">device/location_searching</option>
 <option id="device/mobile_friendly">device/mobile_friendly</option>
 <option id="device/mobile_off">device/mobile_off</option>
 <option id="device/nfc">device/nfc</option>
 <option id="device/screen_lock_landscape">device/screen_lock_landscape</option>
 <option id="device/screen_lock_portrait">device/screen_lock_portrait</option>
 <option id="device/screen_lock_rotation">device/screen_lock_rotation</option>
 <option id="device/screen_rotation">device/screen_rotation</option>
 <option id="device/sd_storage">device/sd_storage</option>
 <option id="device/settings_system_daydream">device/settings_system_daydream</option>
 <option id="device/signal_cellular_4_bar">device/signal_cellular_4_bar</option>
 <option id="device/signal_cellular_alt">device/signal_cellular_alt</option>
 <option id="device/signal_cellular_connected_no_internet_4_bar">device/signal_cellular_connected_no_internet_4_bar</option>
 <option id="device/signal_cellular_no_sim">device/signal_cellular_no_sim</option>
 <option id="device/signal_cellular_null">device/signal_cellular_null</option>
 <option id="device/signal_cellular_off">device/signal_cellular_off</option>
 <option id="device/signal_wifi_4_bar">device/signal_wifi_4_bar</option>
 <option id="device/signal_wifi_4_bar_lock">device/signal_wifi_4_bar_lock</option>
 <option id="device/signal_wifi_off">device/signal_wifi_off</option>
 <option id="device/storage">device/storage</option>
 <option id="device/usb">device/usb</option>
 <option id="device/wallpaper">device/wallpaper</option>
 <option id="device/widgets">device/widgets</option>
 <option id="device/wifi_lock">device/wifi_lock</option>
 <option id="device/wifi_tethering">device/wifi_tethering</option>
 <option id="editor/add_comment">editor/add_comment</option>
 <option id="editor/attach_file">editor/attach_file</option>
 <option id="editor/attach_money">editor/attach_money</option>
 <option id="editor/bar_chart">editor/bar_chart</option>
 <option id="editor/border_all">editor/border_all</option>
 <option id="editor/border_bottom">editor/border_bottom</option>
 <option id="editor/border_clear">editor/border_clear</option>
 <option id="editor/border_horizontal">editor/border_horizontal</option>
 <option id="editor/border_inner">editor/border_inner</option>
 <option id="editor/border_left">editor/border_left</option>
 <option id="editor/border_outer">editor/border_outer</option>
 <option id="editor/border_right">editor/border_right</option>
 <option id="editor/border_style">editor/border_style</option>
 <option id="editor/border_top">editor/border_top</option>
 <option id="editor/border_vertical">editor/border_vertical</option>
 <option id="editor/bubble_chart">editor/bubble_chart</option>
 <option id="editor/drag_handle">editor/drag_handle</option>
 <option id="editor/format_align_center">editor/format_align_center</option>
 <option id="editor/format_align_justify">editor/format_align_justify</option>
 <option id="editor/format_align_left">editor/format_align_left</option>
 <option id="editor/format_align_right">editor/format_align_right</option>
 <option id="editor/format_bold">editor/format_bold</option>
 <option id="editor/format_clear">editor/format_clear</option>
 <option id="editor/format_color_reset">editor/format_color_reset</option>
 <option id="editor/format_indent_decrease">editor/format_indent_decrease</option>
 <option id="editor/format_indent_increase">editor/format_indent_increase</option>
 <option id="editor/format_italic">editor/format_italic</option>
 <option id="editor/format_line_spacing">editor/format_line_spacing</option>
 <option id="editor/format_list_bulleted">editor/format_list_bulleted</option>
 <option id="editor/format_list_numbered">editor/format_list_numbered</option>
 <option id="editor/format_list_numbered_rtl">editor/format_list_numbered_rtl</option>
 <option id="editor/format_paint">editor/format_paint</option>
 <option id="editor/format_quote">editor/format_quote</option>
 <option id="editor/format_shapes">editor/format_shapes</option>
 <option id="editor/format_size">editor/format_size</option>
 <option id="editor/format_strikethrough">editor/format_strikethrough</option>
 <option id="editor/format_textdirection_l_to_r">editor/format_textdirection_l_to_r</option>
 <option id="editor/format_textdirection_r_to_l">editor/format_textdirection_r_to_l</option>
 <option id="editor/format_underlined">editor/format_underlined</option>
 <option id="editor/functions">editor/functions</option>
 <option id="editor/height">editor/height</option>
 <option id="editor/highlight">editor/highlight</option>
 <option id="editor/insert_chart">editor/insert_chart</option>
 <option id="editor/insert_chart_outlined">editor/insert_chart_outlined</option>
 <option id="editor/insert_comment">editor/insert_comment</option>
 <option id="editor/insert_drive_file">editor/insert_drive_file</option>
 <option id="editor/insert_emoticon">editor/insert_emoticon</option>
 <option id="editor/insert_invitation">editor/insert_invitation</option>
 <option id="editor/insert_link">editor/insert_link</option>
 <option id="editor/insert_photo">editor/insert_photo</option>
 <option id="editor/linear_scale">editor/linear_scale</option>
 <option id="editor/merge_type">editor/merge_type</option>
 <option id="editor/mode_comment">editor/mode_comment</option>
 <option id="editor/monetization_on">editor/monetization_on</option>
 <option id="editor/money_off">editor/money_off</option>
 <option id="editor/multiline_chart">editor/multiline_chart</option>
 <option id="editor/notes">editor/notes</option>
 <option id="editor/pie_chart">editor/pie_chart</option>
 <option id="editor/post_add">editor/post_add</option>
 <option id="editor/publish">editor/publish</option>
 <option id="editor/scatter_plot">editor/scatter_plot</option>
 <option id="editor/score">editor/score</option>
 <option id="editor/short_text">editor/short_text</option>
 <option id="editor/show_chart">editor/show_chart</option>
 <option id="editor/space_bar">editor/space_bar</option>
 <option id="editor/strikethrough_s">editor/strikethrough_s</option>
 <option id="editor/table_chart">editor/table_chart</option>
 <option id="editor/text_fields">editor/text_fields</option>
 <option id="editor/title">editor/title</option>
 <option id="editor/vertical_align_bottom">editor/vertical_align_bottom</option>
 <option id="editor/vertical_align_center">editor/vertical_align_center</option>
 <option id="editor/vertical_align_top">editor/vertical_align_top</option>
 <option id="editor/wrap_text">editor/wrap_text</option>
 <option id="file/attachment">file/attachment</option>
 <option id="file/cloud">file/cloud</option>
 <option id="file/cloud_circle">file/cloud_circle</option>
 <option id="file/cloud_done">file/cloud_done</option>
 <option id="file/cloud_download">file/cloud_download</option>
 <option id="file/cloud_off">file/cloud_off</option>
 <option id="file/cloud_queue">file/cloud_queue</option>
 <option id="file/cloud_upload">file/cloud_upload</option>
 <option id="file/create_new_folder">file/create_new_folder</option>
 <option id="file/folder">file/folder</option>
 <option id="file/folder_open">file/folder_open</option>
 <option id="file/folder_shared">file/folder_shared</option>
 <option id="hardware/cast">hardware/cast</option>
 <option id="hardware/cast_connected">hardware/cast_connected</option>
 <option id="hardware/computer">hardware/computer</option>
 <option id="hardware/desktop_mac">hardware/desktop_mac</option>
 <option id="hardware/desktop_windows">hardware/desktop_windows</option>
 <option id="hardware/developer_board">hardware/developer_board</option>
 <option id="hardware/device_hub">hardware/device_hub</option>
 <option id="hardware/device_unknown">hardware/device_unknown</option>
 <option id="hardware/devices_other">hardware/devices_other</option>
 <option id="hardware/dock">hardware/dock</option>
 <option id="hardware/gamepad">hardware/gamepad</option>
 <option id="hardware/headset">hardware/headset</option>
 <option id="hardware/headset_mic">hardware/headset_mic</option>
 <option id="hardware/keyboard">hardware/keyboard</option>
 <option id="hardware/keyboard_arrow_down">hardware/keyboard_arrow_down</option>
 <option id="hardware/keyboard_arrow_left">hardware/keyboard_arrow_left</option>
 <option id="hardware/keyboard_arrow_right">hardware/keyboard_arrow_right</option>
 <option id="hardware/keyboard_arrow_up">hardware/keyboard_arrow_up</option>
 <option id="hardware/keyboard_backspace">hardware/keyboard_backspace</option>
 <option id="hardware/keyboard_capslock">hardware/keyboard_capslock</option>
 <option id="hardware/keyboard_hide">hardware/keyboard_hide</option>
 <option id="hardware/keyboard_return">hardware/keyboard_return</option>
 <option id="hardware/keyboard_tab">hardware/keyboard_tab</option>
 <option id="hardware/keyboard_voice">hardware/keyboard_voice</option>
 <option id="hardware/laptop">hardware/laptop</option>
 <option id="hardware/laptop_chromebook">hardware/laptop_chromebook</option>
 <option id="hardware/laptop_mac">hardware/laptop_mac</option>
 <option id="hardware/laptop_windows">hardware/laptop_windows</option>
 <option id="hardware/memory">hardware/memory</option>
 <option id="hardware/mouse">hardware/mouse</option>
 <option id="hardware/phone_android">hardware/phone_android</option>
 <option id="hardware/phone_iphone">hardware/phone_iphone</option>
 <option id="hardware/phonelink">hardware/phonelink</option>
 <option id="hardware/phonelink_off">hardware/phonelink_off</option>
 <option id="hardware/power_input">hardware/power_input</option>
 <option id="hardware/router">hardware/router</option>
 <option id="hardware/scanner">hardware/scanner</option>
 <option id="hardware/security">hardware/security</option>
 <option id="hardware/sim_card">hardware/sim_card</option>
 <option id="hardware/smartphone">hardware/smartphone</option>
 <option id="hardware/speaker">hardware/speaker</option>
 <option id="hardware/speaker_group">hardware/speaker_group</option>
 <option id="hardware/tablet">hardware/tablet</option>
 <option id="hardware/tablet_android">hardware/tablet_android</option>
 <option id="hardware/tablet_mac">hardware/tablet_mac</option>
 <option id="hardware/toys">hardware/toys</option>
 <option id="hardware/tv">hardware/tv</option>
 <option id="hardware/videogame_asset">hardware/videogame_asset</option>
 <option id="hardware/watch">hardware/watch</option>
 <option id="image/add_a_photo">image/add_a_photo</option>
 <option id="image/add_photo_alternate">image/add_photo_alternate</option>
 <option id="image/add_to_photos">image/add_to_photos</option>
 <option id="image/adjust">image/adjust</option>
 <option id="image/assistant">image/assistant</option>
 <option id="image/assistant_photo">image/assistant_photo</option>
 <option id="image/audiotrack">image/audiotrack</option>
 <option id="image/blur_circular">image/blur_circular</option>
 <option id="image/blur_linear">image/blur_linear</option>
 <option id="image/blur_off">image/blur_off</option>
 <option id="image/blur_on">image/blur_on</option>
 <option id="image/brightness_1">image/brightness_1</option>
 <option id="image/brightness_2">image/brightness_2</option>
 <option id="image/brightness_3">image/brightness_3</option>
 <option id="image/brightness_4">image/brightness_4</option>
 <option id="image/brightness_5">image/brightness_5</option>
 <option id="image/brightness_6">image/brightness_6</option>
 <option id="image/brightness_7">image/brightness_7</option>
 <option id="image/broken_image">image/broken_image</option>
 <option id="image/brush">image/brush</option>
 <option id="image/burst_mode">image/burst_mode</option>
 <option id="image/camera">image/camera</option>
 <option id="image/camera_alt">image/camera_alt</option>
 <option id="image/camera_front">image/camera_front</option>
 <option id="image/camera_rear">image/camera_rear</option>
 <option id="image/camera_roll">image/camera_roll</option>
 <option id="image/center_focus_strong">image/center_focus_strong</option>
 <option id="image/center_focus_weak">image/center_focus_weak</option>
 <option id="image/collections">image/collections</option>
 <option id="image/collections_bookmark">image/collections_bookmark</option>
 <option id="image/color_lens">image/color_lens</option>
 <option id="image/colorize">image/colorize</option>
 <option id="image/compare">image/compare</option>
 <option id="image/control_point">image/control_point</option>
 <option id="image/control_point_duplicate">image/control_point_duplicate</option>
 <option id="image/crop">image/crop</option>
 <option id="image/crop_16_9">image/crop_16_9</option>
 <option id="image/crop_3_2">image/crop_3_2</option>
 <option id="image/crop_5_4">image/crop_5_4</option>
 <option id="image/crop_7_5">image/crop_7_5</option>
 <option id="image/crop_din">image/crop_din</option>
 <option id="image/crop_free">image/crop_free</option>
 <option id="image/crop_landscape">image/crop_landscape</option>
 <option id="image/crop_original">image/crop_original</option>
 <option id="image/crop_portrait">image/crop_portrait</option>
 <option id="image/crop_rotate">image/crop_rotate</option>
 <option id="image/crop_square">image/crop_square</option>
 <option id="image/dehaze">image/dehaze</option>
 <option id="image/details">image/details</option>
 <option id="image/edit">image/edit</option>
 <option id="image/euro">image/euro</option>
 <option id="image/exposure">image/exposure</option>
 <option id="image/exposure_neg_1">image/exposure_neg_1</option>
 <option id="image/exposure_neg_2">image/exposure_neg_2</option>
 <option id="image/exposure_plus_1">image/exposure_plus_1</option>
 <option id="image/exposure_plus_2">image/exposure_plus_2</option>
 <option id="image/exposure_zero">image/exposure_zero</option>
 <option id="image/filter">image/filter</option>
 <option id="image/filter_1">image/filter_1</option>
 <option id="image/filter_2">image/filter_2</option>
 <option id="image/filter_3">image/filter_3</option>
 <option id="image/filter_4">image/filter_4</option>
 <option id="image/filter_5">image/filter_5</option>
 <option id="image/filter_6">image/filter_6</option>
 <option id="image/filter_7">image/filter_7</option>
 <option id="image/filter_8">image/filter_8</option>
 <option id="image/filter_9">image/filter_9</option>
 <option id="image/filter_9_plus">image/filter_9_plus</option>
 <option id="image/filter_b_and_w">image/filter_b_and_w</option>
 <option id="image/filter_center_focus">image/filter_center_focus</option>
 <option id="image/filter_drama">image/filter_drama</option>
 <option id="image/filter_frames">image/filter_frames</option>
 <option id="image/filter_hdr">image/filter_hdr</option>
 <option id="image/filter_none">image/filter_none</option>
 <option id="image/filter_tilt_shift">image/filter_tilt_shift</option>
 <option id="image/filter_vintage">image/filter_vintage</option>
 <option id="image/flare">image/flare</option>
 <option id="image/flash_auto">image/flash_auto</option>
 <option id="image/flash_off">image/flash_off</option>
 <option id="image/flash_on">image/flash_on</option>
 <option id="image/flip">image/flip</option>
 <option id="image/flip_camera_android">image/flip_camera_android</option>
 <option id="image/flip_camera_ios">image/flip_camera_ios</option>
 <option id="image/gradient">image/gradient</option>
 <option id="image/grain">image/grain</option>
 <option id="image/grid_off">image/grid_off</option>
 <option id="image/grid_on">image/grid_on</option>
 <option id="image/hdr_off">image/hdr_off</option>
 <option id="image/hdr_on">image/hdr_on</option>
 <option id="image/hdr_strong">image/hdr_strong</option>
 <option id="image/hdr_weak">image/hdr_weak</option>
 <option id="image/healing">image/healing</option>
 <option id="image/image">image/image</option>
 <option id="image/image_aspect_ratio">image/image_aspect_ratio</option>
 <option id="image/image_search">image/image_search</option>
 <option id="image/iso">image/iso</option>
 <option id="image/landscape">image/landscape</option>
 <option id="image/leak_add">image/leak_add</option>
 <option id="image/leak_remove">image/leak_remove</option>
 <option id="image/lens">image/lens</option>
 <option id="image/linked_camera">image/linked_camera</option>
 <option id="image/looks">image/looks</option>
 <option id="image/looks_3">image/looks_3</option>
 <option id="image/looks_4">image/looks_4</option>
 <option id="image/looks_5">image/looks_5</option>
 <option id="image/looks_6">image/looks_6</option>
 <option id="image/looks_one">image/looks_one</option>
 <option id="image/looks_two">image/looks_two</option>
 <option id="image/loupe">image/loupe</option>
 <option id="image/monochrome_photos">image/monochrome_photos</option>
 <option id="image/movie_creation">image/movie_creation</option>
 <option id="image/movie_filter">image/movie_filter</option>
 <option id="image/music_note">image/music_note</option>
 <option id="image/music_off">image/music_off</option>
 <option id="image/nature">image/nature</option>
 <option id="image/nature_people">image/nature_people</option>
 <option id="image/navigate_before">image/navigate_before</option>
 <option id="image/navigate_next">image/navigate_next</option>
 <option id="image/palette">image/palette</option>
 <option id="image/panorama">image/panorama</option>
 <option id="image/panorama_fish_eye">image/panorama_fish_eye</option>
 <option id="image/panorama_horizontal">image/panorama_horizontal</option>
 <option id="image/panorama_vertical">image/panorama_vertical</option>
 <option id="image/panorama_wide_angle">image/panorama_wide_angle</option>
 <option id="image/photo">image/photo</option>
 <option id="image/photo_album">image/photo_album</option>
 <option id="image/photo_camera">image/photo_camera</option>
 <option id="image/photo_filter">image/photo_filter</option>
 <option id="image/photo_library">image/photo_library</option>
 <option id="image/photo_size_select_actual">image/photo_size_select_actual</option>
 <option id="image/photo_size_select_large">image/photo_size_select_large</option>
 <option id="image/photo_size_select_small">image/photo_size_select_small</option>
 <option id="image/picture_as_pdf">image/picture_as_pdf</option>
 <option id="image/portrait">image/portrait</option>
 <option id="image/remove_red_eye">image/remove_red_eye</option>
 <option id="image/rotate_90_degrees_ccw">image/rotate_90_degrees_ccw</option>
 <option id="image/rotate_left">image/rotate_left</option>
 <option id="image/rotate_right">image/rotate_right</option>
 <option id="image/shutter_speed">image/shutter_speed</option>
 <option id="image/slideshow">image/slideshow</option>
 <option id="image/straighten">image/straighten</option>
 <option id="image/style">image/style</option>
 <option id="image/switch_camera">image/switch_camera</option>
 <option id="image/switch_video">image/switch_video</option>
 <option id="image/tag_faces">image/tag_faces</option>
 <option id="image/texture">image/texture</option>
 <option id="image/timelapse">image/timelapse</option>
 <option id="image/timer">image/timer</option>
 <option id="image/timer_10">image/timer_10</option>
 <option id="image/timer_3">image/timer_3</option>
 <option id="image/timer_off">image/timer_off</option>
 <option id="image/tonality">image/tonality</option>
 <option id="image/transform">image/transform</option>
 <option id="image/tune">image/tune</option>
 <option id="image/view_comfy">image/view_comfy</option>
 <option id="image/view_compact">image/view_compact</option>
 <option id="image/vignette">image/vignette</option>
 <option id="image/wb_auto">image/wb_auto</option>
 <option id="image/wb_cloudy">image/wb_cloudy</option>
 <option id="image/wb_incandescent">image/wb_incandescent</option>
 <option id="image/wb_iridescent">image/wb_iridescent</option>
 <option id="image/wb_sunny">image/wb_sunny</option>
 <option id="maps/360">maps/360</option>
 <option id="maps/atm">maps/atm</option>
 <option id="maps/beenhere">maps/beenhere</option>
 <option id="maps/category">maps/category</option>
 <option id="maps/compass_calibration">maps/compass_calibration</option>
 <option id="maps/departure_board">maps/departure_board</option>
 <option id="maps/directions">maps/directions</option>
 <option id="maps/directions_bike">maps/directions_bike</option>
 <option id="maps/directions_boat">maps/directions_boat</option>
 <option id="maps/directions_bus">maps/directions_bus</option>
 <option id="maps/directions_car">maps/directions_car</option>
 <option id="maps/directions_railway">maps/directions_railway</option>
 <option id="maps/directions_run">maps/directions_run</option>
 <option id="maps/directions_subway">maps/directions_subway</option>
 <option id="maps/directions_transit">maps/directions_transit</option>
 <option id="maps/directions_walk">maps/directions_walk</option>
 <option id="maps/edit_attributes">maps/edit_attributes</option>
 <option id="maps/ev_station">maps/ev_station</option>
 <option id="maps/fastfood">maps/fastfood</option>
 <option id="maps/flight">maps/flight</option>
 <option id="maps/hotel">maps/hotel</option>
 <option id="maps/layers">maps/layers</option>
 <option id="maps/layers_clear">maps/layers_clear</option>
 <option id="maps/local_activity">maps/local_activity</option>
 <option id="maps/local_airport">maps/local_airport</option>
 <option id="maps/local_atm">maps/local_atm</option>
 <option id="maps/local_bar">maps/local_bar</option>
 <option id="maps/local_cafe">maps/local_cafe</option>
 <option id="maps/local_car_wash">maps/local_car_wash</option>
 <option id="maps/local_convenience_store">maps/local_convenience_store</option>
 <option id="maps/local_dining">maps/local_dining</option>
 <option id="maps/local_drink">maps/local_drink</option>
 <option id="maps/local_florist">maps/local_florist</option>
 <option id="maps/local_gas_station">maps/local_gas_station</option>
 <option id="maps/local_grocery_store">maps/local_grocery_store</option>
 <option id="maps/local_hospital">maps/local_hospital</option>
 <option id="maps/local_hotel">maps/local_hotel</option>
 <option id="maps/local_laundry_service">maps/local_laundry_service</option>
 <option id="maps/local_library">maps/local_library</option>
 <option id="maps/local_mall">maps/local_mall</option>
 <option id="maps/local_movies">maps/local_movies</option>
 <option id="maps/local_offer">maps/local_offer</option>
 <option id="maps/local_parking">maps/local_parking</option>
 <option id="maps/local_pharmacy">maps/local_pharmacy</option>
 <option id="maps/local_phone">maps/local_phone</option>
 <option id="maps/local_pizza">maps/local_pizza</option>
 <option id="maps/local_play">maps/local_play</option>
 <option id="maps/local_post_office">maps/local_post_office</option>
 <option id="maps/local_printshop">maps/local_printshop</option>
 <option id="maps/local_see">maps/local_see</option>
 <option id="maps/local_shipping">maps/local_shipping</option>
 <option id="maps/local_taxi">maps/local_taxi</option>
 <option id="maps/map">maps/map</option>
 <option id="maps/menu_book">maps/menu_book</option>
 <option id="maps/money">maps/money</option>
 <option id="maps/museum">maps/museum</option>
 <option id="maps/my_location">maps/my_location</option>
 <option id="maps/navigation">maps/navigation</option>
 <option id="maps/near_me">maps/near_me</option>
 <option id="maps/person_pin">maps/person_pin</option>
 <option id="maps/rate_review">maps/rate_review</option>
 <option id="maps/restaurant">maps/restaurant</option>
 <option id="maps/restaurant_menu">maps/restaurant_menu</option>
 <option id="maps/satellite">maps/satellite</option>
 <option id="maps/store_mall_directory">maps/store_mall_directory</option>
 <option id="maps/streetview">maps/streetview</option>
 <option id="maps/subway">maps/subway</option>
 <option id="maps/terrain">maps/terrain</option>
 <option id="maps/traffic">maps/traffic</option>
 <option id="maps/train">maps/train</option>
 <option id="maps/tram">maps/tram</option>
 <option id="maps/transfer_within_a_station">maps/transfer_within_a_station</option>
 <option id="maps/transit_enterexit">maps/transit_enterexit</option>
 <option id="maps/trip_origin">maps/trip_origin</option>
 <option id="maps/zoom_out_map">maps/zoom_out_map</option>
 <option id="navigation/apps">navigation/apps</option>
 <option id="navigation/arrow_back">navigation/arrow_back</option>
 <option id="navigation/arrow_back_ios">navigation/arrow_back_ios</option>
 <option id="navigation/arrow_downward">navigation/arrow_downward</option>
 <option id="navigation/arrow_drop_down">navigation/arrow_drop_down</option>
 <option id="navigation/arrow_drop_down_circle">navigation/arrow_drop_down_circle</option>
 <option id="navigation/arrow_drop_up">navigation/arrow_drop_up</option>
 <option id="navigation/arrow_forward">navigation/arrow_forward</option>
 <option id="navigation/arrow_forward_ios">navigation/arrow_forward_ios</option>
 <option id="navigation/arrow_left">navigation/arrow_left</option>
 <option id="navigation/arrow_right">navigation/arrow_right</option>
 <option id="navigation/arrow_upward">navigation/arrow_upward</option>
 <option id="navigation/cancel">navigation/cancel</option>
 <option id="navigation/check">navigation/check</option>
 <option id="navigation/chevron_left">navigation/chevron_left</option>
 <option id="navigation/chevron_right">navigation/chevron_right</option>
 <option id="navigation/close">navigation/close</option>
 <option id="navigation/double_arrow">navigation/double_arrow</option>
 <option id="navigation/expand_less">navigation/expand_less</option>
 <option id="navigation/expand_more">navigation/expand_more</option>
 <option id="navigation/first_page">navigation/first_page</option>
 <option id="navigation/fullscreen">navigation/fullscreen</option>
 <option id="navigation/fullscreen_exit">navigation/fullscreen_exit</option>
 <option id="navigation/home_work">navigation/home_work</option>
 <option id="navigation/last_page">navigation/last_page</option>
 <option id="navigation/menu">navigation/menu</option>
 <option id="navigation/menu_open">navigation/menu_open</option>
 <option id="navigation/more_horiz">navigation/more_horiz</option>
 <option id="navigation/more_vert">navigation/more_vert</option>
 <option id="navigation/refresh">navigation/refresh</option>
 <option id="navigation/subdirectory_arrow_left">navigation/subdirectory_arrow_left</option>
 <option id="navigation/subdirectory_arrow_right">navigation/subdirectory_arrow_right</option>
 <option id="navigation/unfold_less">navigation/unfold_less</option>
 <option id="navigation/unfold_more">navigation/unfold_more</option>
 <option id="notification/account_tree">notification/account_tree</option>
 <option id="notification/adb">notification/adb</option>
 <option id="notification/airline_seat_flat">notification/airline_seat_flat</option>
 <option id="notification/airline_seat_flat_angled">notification/airline_seat_flat_angled</option>
 <option id="notification/airline_seat_individual_suite">notification/airline_seat_individual_suite</option>
 <option id="notification/airline_seat_legroom_extra">notification/airline_seat_legroom_extra</option>
 <option id="notification/airline_seat_legroom_normal">notification/airline_seat_legroom_normal</option>
 <option id="notification/airline_seat_legroom_reduced">notification/airline_seat_legroom_reduced</option>
 <option id="notification/airline_seat_recline_extra">notification/airline_seat_recline_extra</option>
 <option id="notification/airline_seat_recline_normal">notification/airline_seat_recline_normal</option>
 <option id="notification/bluetooth_audio">notification/bluetooth_audio</option>
 <option id="notification/confirmation_number">notification/confirmation_number</option>
 <option id="notification/disc_full">notification/disc_full</option>
 <option id="notification/drive_eta">notification/drive_eta</option>
 <option id="notification/enhanced_encryption">notification/enhanced_encryption</option>
 <option id="notification/event_available">notification/event_available</option>
 <option id="notification/event_busy">notification/event_busy</option>
 <option id="notification/event_note">notification/event_note</option>
 <option id="notification/folder_special">notification/folder_special</option>
 <option id="notification/live_tv">notification/live_tv</option>
 <option id="notification/mms">notification/mms</option>
 <option id="notification/more">notification/more</option>
 <option id="notification/network_check">notification/network_check</option>
 <option id="notification/network_locked">notification/network_locked</option>
 <option id="notification/no_encryption">notification/no_encryption</option>
 <option id="notification/ondemand_video">notification/ondemand_video</option>
 <option id="notification/personal_video">notification/personal_video</option>
 <option id="notification/phone_bluetooth_speaker">notification/phone_bluetooth_speaker</option>
 <option id="notification/phone_callback">notification/phone_callback</option>
 <option id="notification/phone_forwarded">notification/phone_forwarded</option>
 <option id="notification/phone_in_talk">notification/phone_in_talk</option>
 <option id="notification/phone_locked">notification/phone_locked</option>
 <option id="notification/phone_missed">notification/phone_missed</option>
 <option id="notification/phone_paused">notification/phone_paused</option>
 <option id="notification/power">notification/power</option>
 <option id="notification/power_off">notification/power_off</option>
 <option id="notification/priority_high">notification/priority_high</option>
 <option id="notification/sd_card">notification/sd_card</option>
 <option id="notification/sms">notification/sms</option>
 <option id="notification/sms_failed">notification/sms_failed</option>
 <option id="notification/sync">notification/sync</option>
 <option id="notification/sync_disabled">notification/sync_disabled</option>
 <option id="notification/sync_problem">notification/sync_problem</option>
 <option id="notification/system_update">notification/system_update</option>
 <option id="notification/tap_and_play">notification/tap_and_play</option>
 <option id="notification/time_to_leave">notification/time_to_leave</option>
 <option id="notification/tv_off">notification/tv_off</option>
 <option id="notification/vibration">notification/vibration</option>
 <option id="notification/voice_chat">notification/voice_chat</option>
 <option id="notification/vpn_lock">notification/vpn_lock</option>
 <option id="notification/wc">notification/wc</option>
 <option id="notification/wifi">notification/wifi</option>
 <option id="notification/wifi_off">notification/wifi_off</option>
 <option id="places/ac_unit">places/ac_unit</option>
 <option id="places/airport_shuttle">places/airport_shuttle</option>
 <option id="places/all_inclusive">places/all_inclusive</option>
 <option id="places/apartment">places/apartment</option>
 <option id="places/bathtub">places/bathtub</option>
 <option id="places/beach_access">places/beach_access</option>
 <option id="places/business_center">places/business_center</option>
 <option id="places/casino">places/casino</option>
 <option id="places/child_care">places/child_care</option>
 <option id="places/child_friendly">places/child_friendly</option>
 <option id="places/fitness_center">places/fitness_center</option>
 <option id="places/free_breakfast">places/free_breakfast</option>
 <option id="places/golf_course">places/golf_course</option>
 <option id="places/hot_tub">places/hot_tub</option>
 <option id="places/house">places/house</option>
 <option id="places/kitchen">places/kitchen</option>
 <option id="places/meeting_room">places/meeting_room</option>
 <option id="places/no_meeting_room">places/no_meeting_room</option>
 <option id="places/pool">places/pool</option>
 <option id="places/room_service">places/room_service</option>
 <option id="places/rv_hookup">places/rv_hookup</option>
 <option id="places/smoke_free">places/smoke_free</option>
 <option id="places/smoking_rooms">places/smoking_rooms</option>
 <option id="places/spa">places/spa</option>
 <option id="places/storefront">places/storefront</option>
 <option id="social/cake">social/cake</option>
 <option id="social/deck">social/deck</option>
 <option id="social/emoji_emotions">social/emoji_emotions</option>
 <option id="social/emoji_events">social/emoji_events</option>
 <option id="social/emoji_flags">social/emoji_flags</option>
 <option id="social/emoji_food_beverage">social/emoji_food_beverage</option>
 <option id="social/emoji_nature">social/emoji_nature</option>
 <option id="social/emoji_objects">social/emoji_objects</option>
 <option id="social/emoji_people">social/emoji_people</option>
 <option id="social/emoji_symbols">social/emoji_symbols</option>
 <option id="social/emoji_transportation">social/emoji_transportation</option>
 <option id="social/fireplace">social/fireplace</option>
 <option id="social/group">social/group</option>
 <option id="social/group_add">social/group_add</option>
 <option id="social/king_bed">social/king_bed</option>
 <option id="social/location_city">social/location_city</option>
 <option id="social/mood">social/mood</option>
 <option id="social/mood_bad">social/mood_bad</option>
 <option id="social/nights_stay">social/nights_stay</option>
 <option id="social/notifications">social/notifications</option>
 <option id="social/notifications_active">social/notifications_active</option>
 <option id="social/notifications_none">social/notifications_none</option>
 <option id="social/notifications_off">social/notifications_off</option>
 <option id="social/notifications_paused">social/notifications_paused</option>
 <option id="social/outdoor_grill">social/outdoor_grill</option>
 <option id="social/pages">social/pages</option>
 <option id="social/party_mode">social/party_mode</option>
 <option id="social/people">social/people</option>
 <option id="social/people_alt">social/people_alt</option>
 <option id="social/people_outline">social/people_outline</option>
 <option id="social/person">social/person</option>
 <option id="social/person_add">social/person_add</option>
 <option id="social/person_outline">social/person_outline</option>
 <option id="social/plus_one">social/plus_one</option>
 <option id="social/poll">social/poll</option>
 <option id="social/public">social/public</option>
 <option id="social/school">social/school</option>
 <option id="social/sentiment_dissatisfied">social/sentiment_dissatisfied</option>
 <option id="social/sentiment_satisfied">social/sentiment_satisfied</option>
 <option id="social/sentiment_very_dissatisfied">social/sentiment_very_dissatisfied</option>
 <option id="social/sentiment_very_satisfied">social/sentiment_very_satisfied</option>
 <option id="social/share">social/share</option>
 <option id="social/single_bed">social/single_bed</option>
 <option id="social/sports">social/sports</option>
 <option id="social/sports_baseball">social/sports_baseball</option>
 <option id="social/sports_basketball">social/sports_basketball</option>
 <option id="social/sports_cricket">social/sports_cricket</option>
 <option id="social/sports_esports">social/sports_esports</option>
 <option id="social/sports_football">social/sports_football</option>
 <option id="social/sports_golf">social/sports_golf</option>
 <option id="social/sports_handball">social/sports_handball</option>
 <option id="social/sports_hockey">social/sports_hockey</option>
 <option id="social/sports_kabaddi">social/sports_kabaddi</option>
 <option id="social/sports_mma">social/sports_mma</option>
 <option id="social/sports_motorsports">social/sports_motorsports</option>
 <option id="social/sports_rugby">social/sports_rugby</option>
 <option id="social/sports_soccer">social/sports_soccer</option>
 <option id="social/sports_tennis">social/sports_tennis</option>
 <option id="social/sports_volleyball">social/sports_volleyball</option>
 <option id="social/thumb_down_alt">social/thumb_down_alt</option>
 <option id="social/thumb_up_alt">social/thumb_up_alt</option>
 <option id="social/whatshot">social/whatshot</option>
 <option id="toggle/check_box">toggle/check_box</option>
 <option id="toggle/check_box_outline_blank">toggle/check_box_outline_blank</option>
 <option id="toggle/indeterminate_check_box">toggle/indeterminate_check_box</option>
 <option id="toggle/radio_button_checked">toggle/radio_button_checked</option>
 <option id="toggle/radio_button_unchecked">toggle/radio_button_unchecked</option>
 <option id="toggle/star">toggle/star</option>
 <option id="toggle/star_border">toggle/star_border</option>
 <option id="toggle/star_half">toggle/star_half</option>
 <option id="toggle/toggle_off">toggle/toggle_off</option>
 <option id="toggle/toggle_on">toggle/toggle_on</option>
</icons>
